{
  "analyzed": "2026-04-10 23:39:17",
  "defensive": [
    {
      "code": "005930",
      "name": "삼성전자",
      "price": 206000,
      "change": 2000,
      "changePercent": 2.0,
      "volume": 18229163,
      "direction": "up",
      "score": 80.0,
      "reason": "안정적인 2.00% 변동"
    },
    {
      "code": "000660",
      "name": "SK하이닉스",
      "price": 1027000,
      "change": 29000,
      "changePercent": 2.0,
      "volume": 3038008,
      "direction": "up",
      "score": 80.0,
      "reason": "안정적인 2.00% 변동"
    },
    {
      "code": "005490",
      "name": "POSCO홀딩스",
      "price": 369000,
      "change": 2000,
      "changePercent": 2.0,
      "volume": 246719,
      "direction": "up",
      "score": 80.0,
      "reason": "안정적인 2.00% 변동"
    },
    {
      "code": "035420",
      "name": "NAVER",
      "price": 202000,
      "change": 500,
      "changePercent": 2.0,
      "volume": 525142,
      "direction": "up",
      "score": 80.0,
      "reason": "안정적인 2.00% 변동"
    },
    {
      "code": "051910",
      "name": "LG화학",
      "price": 356000,
      "change": 1000,
      "changePercent": 2.0,
      "volume": 283205,
      "direction": "up",
      "score": 80.0,
      "reason": "안정적인 2.00% 변동"
    },
    {
      "code": "006400",
      "name": "삼성SDI",
      "price": 481000,
      "change": 1000,
      "changePercent": 2.0,
      "volume": 550626,
      "direction": "up",
      "score": 80.0,
      "reason": "안정적인 2.00% 변동"
    },
    {
      "code": "035720",
      "name": "카카오",
      "price": 47700,
      "change": 400,
      "changePercent": 2.0,
      "volume": 691399,
      "direction": "up",
      "score": 80.0,
      "reason": "안정적인 2.00% 변동"
    },
    {
      "code": "028260",
      "name": "삼성물산",
      "price": 302500,
      "change": 2500,
      "changePercent": 2.0,
      "volume": 256873,
      "direction": "up",
      "score": 80.0,
      "reason": "안정적인 2.00% 변동"
    },
    {
      "code": "012330",
      "name": "현대모비스",
      "price": 402500,
      "change": 1000,
      "changePercent": 2.0,
      "volume": 255234,
      "direction": "up",
      "score": 80.0,
      "reason": "안정적인 2.00% 변동"
    },
    {
      "code": "066570",
      "name": "LG전자",
      "price": 118400,
      "change": 1200,
      "changePercent": 2.0,
      "volume": 608715,
      "direction": "up",
      "score": 80.0,
      "reason": "안정적인 2.00% 변동"
    }
  ],
  "aggressive": [
    {
      "code": "000270",
      "name": "기아",
      "price": 149000,
      "change": 1500,
      "changePercent": 5.0,
      "volume": 1757754,
      "direction": "up",
      "score": 51.757754,
      "reason": "강한 상승세 +5.00%"
    },
    {
      "code": "017670",
      "name": "SK텔레콤",
      "price": 93000,
      "change": 800,
      "changePercent": 5.0,
      "volume": 1372619,
      "direction": "up",
      "score": 51.372619,
      "reason": "강한 상승세 +5.00%"
    },
    {
      "code": "096770",
      "name": "SK이노베이션",
      "price": 122400,
      "change": 1600,
      "changePercent": 5.0,
      "volume": 291430,
      "direction": "up",
      "score": 50.29143,
      "reason": "강한 상승세 +5.00%"
    },
    {
      "code": "373220",
      "name": "LG에너지솔루션",
      "price": 412000,
      "change": 9000,
      "changePercent": 5.0,
      "volume": 273188,
      "direction": "up",
      "score": 50.273188,
      "reason": "강한 상승세 +5.00%"
    },
    {
      "code": "207940",
      "name": "삼성바이오로직스",
      "price": 1571000,
      "change": 9000,
      "changePercent": 5.0,
      "volume": 30706,
      "direction": "up",
      "score": 50.030706,
      "reason": "강한 상승세 +5.00%"
    },
    {
      "code": "005930",
      "name": "삼성전자",
      "price": 206000,
      "change": 2000,
      "changePercent": 2.0,
      "volume": 18229163,
      "direction": "up",
      "score": 38.229163,
      "reason": "강한 상승세 +2.00%"
    },
    {
      "code": "005380",
      "name": "현대차",
      "price": 489500,
      "change": 0,
      "changePercent": 3.0,
      "volume": 812711,
      "direction": "flat",
      "score": 30.812711,
      "reason": "강한 상승세 +3.00%"
    },
    {
      "code": "000660",
      "name": "SK하이닉스",
      "price": 1027000,
      "change": 29000,
      "changePercent": 2.0,
      "volume": 3038008,
      "direction": "up",
      "score": 23.038008,
      "reason": "강한 상승세 +2.00%"
    },
    {
      "code": "086790",
      "name": "하나금융지주",
      "price": 119500,
      "change": 2400,
      "changePercent": 2.0,
      "volume": 722219,
      "direction": "up",
      "score": 20.722219,
      "reason": "강한 상승세 +2.00%"
    },
    {
      "code": "035720",
      "name": "카카오",
      "price": 47700,
      "change": 400,
      "changePercent": 2.0,
      "volume": 691399,
      "direction": "up",
      "score": 20.691399,
      "reason": "강한 상승세 +2.00%"
    }
  ],
  "summary": {
    "total_stocks": 20,
    "avg_change": 2.8,
    "positive_stocks": 20,
    "negative_stocks": 0
  }
}