{
  "analyzed": "2026-05-20 00:09:47",
  "defensive": [
    {
      "code": "005930",
      "name": "삼성전자",
      "price": 277000,
      "change": 1500,
      "changePercent": 2.0,
      "volume": 3191078,
      "direction": "up",
      "score": 80.0,
      "reason": "안정적인 2.00% 변동"
    },
    {
      "code": "012330",
      "name": "현대모비스",
      "price": 535000,
      "change": 10000,
      "changePercent": 2.0,
      "volume": 65684,
      "direction": "up",
      "score": 80.0,
      "reason": "안정적인 2.00% 변동"
    },
    {
      "code": "017670",
      "name": "SK텔레콤",
      "price": 99500,
      "change": 1800,
      "changePercent": 2.0,
      "volume": 78824,
      "direction": "up",
      "score": 80.0,
      "reason": "안정적인 2.00% 변동"
    },
    {
      "code": "096770",
      "name": "SK이노베이션",
      "price": 119800,
      "change": 200,
      "changePercent": 2.0,
      "volume": 63109,
      "direction": "up",
      "score": 80.0,
      "reason": "안정적인 2.00% 변동"
    },
    {
      "code": "055550",
      "name": "신한지주",
      "price": 94400,
      "change": 500,
      "changePercent": 2.0,
      "volume": 96540,
      "direction": "up",
      "score": 80.0,
      "reason": "안정적인 2.00% 변동"
    },
    {
      "code": "000660",
      "name": "SK하이닉스",
      "price": 1717500,
      "change": 27500,
      "changePercent": 5.0,
      "volume": 731718,
      "direction": "up",
      "score": 50.0,
      "reason": "안정적인 5.00% 변동"
    },
    {
      "code": "373220",
      "name": "LG에너지솔루션",
      "price": 393000,
      "change": 7000,
      "changePercent": 5.0,
      "volume": 32937,
      "direction": "up",
      "score": 50.0,
      "reason": "안정적인 5.00% 변동"
    },
    {
      "code": "207940",
      "name": "삼성바이오로직스",
      "price": 1317000,
      "change": 29000,
      "changePercent": 5.0,
      "volume": 7068,
      "direction": "up",
      "score": 50.0,
      "reason": "안정적인 5.00% 변동"
    },
    {
      "code": "005490",
      "name": "POSCO홀딩스",
      "price": 428000,
      "change": 12500,
      "changePercent": 5.0,
      "volume": 54919,
      "direction": "up",
      "score": 50.0,
      "reason": "안정적인 5.00% 변동"
    },
    {
      "code": "035420",
      "name": "NAVER",
      "price": 195700,
      "change": 2400,
      "changePercent": 5.0,
      "volume": 86792,
      "direction": "up",
      "score": 50.0,
      "reason": "안정적인 5.00% 변동"
    }
  ],
  "aggressive": [
    {
      "code": "000660",
      "name": "SK하이닉스",
      "price": 1717500,
      "change": 27500,
      "changePercent": 5.0,
      "volume": 731718,
      "direction": "up",
      "score": 50.731718,
      "reason": "강한 상승세 +5.00%"
    },
    {
      "code": "066570",
      "name": "LG전자",
      "price": 181600,
      "change": 10100,
      "changePercent": 5.0,
      "volume": 444067,
      "direction": "up",
      "score": 50.444067,
      "reason": "강한 상승세 +5.00%"
    },
    {
      "code": "005380",
      "name": "현대차",
      "price": 591000,
      "change": 13000,
      "changePercent": 5.0,
      "volume": 178657,
      "direction": "up",
      "score": 50.178657,
      "reason": "강한 상승세 +5.00%"
    },
    {
      "code": "086790",
      "name": "하나금융지주",
      "price": 114900,
      "change": 400,
      "changePercent": 5.0,
      "volume": 137576,
      "direction": "up",
      "score": 50.137576,
      "reason": "강한 상승세 +5.00%"
    },
    {
      "code": "035720",
      "name": "카카오",
      "price": 41400,
      "change": 200,
      "changePercent": 5.0,
      "volume": 121115,
      "direction": "up",
      "score": 50.121115,
      "reason": "강한 상승세 +5.00%"
    },
    {
      "code": "000270",
      "name": "기아",
      "price": 152700,
      "change": 2200,
      "changePercent": 5.0,
      "volume": 120373,
      "direction": "up",
      "score": 50.120373,
      "reason": "강한 상승세 +5.00%"
    },
    {
      "code": "105560",
      "name": "KB금융",
      "price": 152200,
      "change": 600,
      "changePercent": 5.0,
      "volume": 100962,
      "direction": "up",
      "score": 50.100962,
      "reason": "강한 상승세 +5.00%"
    },
    {
      "code": "035420",
      "name": "NAVER",
      "price": 195700,
      "change": 2400,
      "changePercent": 5.0,
      "volume": 86792,
      "direction": "up",
      "score": 50.086792,
      "reason": "강한 상승세 +5.00%"
    },
    {
      "code": "003550",
      "name": "LG",
      "price": 101900,
      "change": 3400,
      "changePercent": 5.0,
      "volume": 67913,
      "direction": "up",
      "score": 50.067913,
      "reason": "강한 상승세 +5.00%"
    },
    {
      "code": "006400",
      "name": "삼성SDI",
      "price": 566000,
      "change": 21000,
      "changePercent": 5.0,
      "volume": 60860,
      "direction": "up",
      "score": 50.06086,
      "reason": "강한 상승세 +5.00%"
    }
  ],
  "summary": {
    "total_stocks": 20,
    "avg_change": 4.25,
    "positive_stocks": 20,
    "negative_stocks": 0
  }
}