{
  "analyzed": "2026-02-11 05:19:22",
  "defensive": [
    {
      "code": "005930",
      "name": "삼성전자",
      "price": 168250,
      "change": 2450,
      "changePercent": 2.0,
      "volume": 18192153,
      "direction": "up",
      "score": 80.0,
      "reason": "안정적인 2.00% 변동"
    },
    {
      "code": "373220",
      "name": "LG에너지솔루션",
      "price": 391500,
      "change": 1000,
      "changePercent": 2.0,
      "volume": 149174,
      "direction": "up",
      "score": 80.0,
      "reason": "안정적인 2.00% 변동"
    },
    {
      "code": "207940",
      "name": "삼성바이오로직스",
      "price": 1717000,
      "change": 7000,
      "changePercent": 2.0,
      "volume": 24493,
      "direction": "up",
      "score": 80.0,
      "reason": "안정적인 2.00% 변동"
    },
    {
      "code": "005490",
      "name": "POSCO홀딩스",
      "price": 372000,
      "change": 1000,
      "changePercent": 2.0,
      "volume": 302077,
      "direction": "up",
      "score": 80.0,
      "reason": "안정적인 2.00% 변동"
    },
    {
      "code": "035420",
      "name": "NAVER",
      "price": 258250,
      "change": 4250,
      "changePercent": 2.0,
      "volume": 947842,
      "direction": "up",
      "score": 80.0,
      "reason": "안정적인 2.00% 변동"
    },
    {
      "code": "051910",
      "name": "LG화학",
      "price": 325000,
      "change": 4000,
      "changePercent": 2.0,
      "volume": 233899,
      "direction": "up",
      "score": 80.0,
      "reason": "안정적인 2.00% 변동"
    },
    {
      "code": "035720",
      "name": "카카오",
      "price": 58800,
      "change": 500,
      "changePercent": 2.0,
      "volume": 1334064,
      "direction": "up",
      "score": 80.0,
      "reason": "안정적인 2.00% 변동"
    },
    {
      "code": "012330",
      "name": "현대모비스",
      "price": 443000,
      "change": 6000,
      "changePercent": 2.0,
      "volume": 225033,
      "direction": "up",
      "score": 80.0,
      "reason": "안정적인 2.00% 변동"
    },
    {
      "code": "066570",
      "name": "LG전자",
      "price": 126950,
      "change": 22950,
      "changePercent": 2.0,
      "volume": 10945610,
      "direction": "up",
      "score": 80.0,
      "reason": "안정적인 2.00% 변동"
    },
    {
      "code": "003550",
      "name": "LG",
      "price": 99200,
      "change": 6300,
      "changePercent": 2.0,
      "volume": 582123,
      "direction": "up",
      "score": 80.0,
      "reason": "안정적인 2.00% 변동"
    }
  ],
  "aggressive": [
    {
      "code": "000660",
      "name": "SK하이닉스",
      "price": 870000,
      "change": 6000,
      "changePercent": 5.0,
      "volume": 2487132,
      "direction": "up",
      "score": 52.487132,
      "reason": "강한 상승세 +5.00%"
    },
    {
      "code": "006400",
      "name": "삼성SDI",
      "price": 378000,
      "change": 3000,
      "changePercent": 5.0,
      "volume": 288923,
      "direction": "up",
      "score": 50.288923,
      "reason": "강한 상승세 +5.00%"
    },
    {
      "code": "028260",
      "name": "삼성물산",
      "price": 316000,
      "change": 1000,
      "changePercent": 5.0,
      "volume": 191333,
      "direction": "up",
      "score": 50.191333,
      "reason": "강한 상승세 +5.00%"
    },
    {
      "code": "005930",
      "name": "삼성전자",
      "price": 168250,
      "change": 2450,
      "changePercent": 2.0,
      "volume": 18192153,
      "direction": "up",
      "score": 38.192153000000005,
      "reason": "강한 상승세 +2.00%"
    },
    {
      "code": "066570",
      "name": "LG전자",
      "price": 126950,
      "change": 22950,
      "changePercent": 2.0,
      "volume": 10945610,
      "direction": "up",
      "score": 30.945610000000002,
      "reason": "강한 상승세 +2.00%"
    },
    {
      "code": "005380",
      "name": "현대차",
      "price": 504500,
      "change": 24000,
      "changePercent": 2.0,
      "volume": 2249474,
      "direction": "up",
      "score": 22.249474,
      "reason": "강한 상승세 +2.00%"
    },
    {
      "code": "105560",
      "name": "KB금융",
      "price": 163700,
      "change": 8200,
      "changePercent": 2.0,
      "volume": 1609873,
      "direction": "up",
      "score": 21.609873,
      "reason": "강한 상승세 +2.00%"
    },
    {
      "code": "035720",
      "name": "카카오",
      "price": 58800,
      "change": 500,
      "changePercent": 2.0,
      "volume": 1334064,
      "direction": "up",
      "score": 21.334064,
      "reason": "강한 상승세 +2.00%"
    },
    {
      "code": "055550",
      "name": "신한지주",
      "price": 100300,
      "change": 2400,
      "changePercent": 2.0,
      "volume": 1256796,
      "direction": "up",
      "score": 21.256796,
      "reason": "강한 상승세 +2.00%"
    },
    {
      "code": "000270",
      "name": "기아",
      "price": 160500,
      "change": 5800,
      "changePercent": 2.0,
      "volume": 1206416,
      "direction": "up",
      "score": 21.206416,
      "reason": "강한 상승세 +2.00%"
    }
  ],
  "summary": {
    "total_stocks": 20,
    "avg_change": 2.45,
    "positive_stocks": 20,
    "negative_stocks": 0
  }
}