{
  "updated": "2026-03-26T23:36:18.685639+00:00",
  "updatedKST": "2026-03-27 08:36:18",
  "stocks": [
    {
      "code": "005930",
      "name": "삼성전자",
      "price": 180100,
      "change": 0,
      "changePercent": 3.0,
      "volume": 0,
      "direction": "flat"
    },
    {
      "code": "000660",
      "name": "SK하이닉스",
      "price": 933000,
      "change": 0,
      "changePercent": 3.0,
      "volume": 0,
      "direction": "flat"
    },
    {
      "code": "373220",
      "name": "LG에너지솔루션",
      "price": 384500,
      "change": 0,
      "changePercent": 3.0,
      "volume": 0,
      "direction": "flat"
    },
    {
      "code": "207940",
      "name": "삼성바이오로직스",
      "price": 1585000,
      "change": 0,
      "changePercent": 3.0,
      "volume": 0,
      "direction": "flat"
    },
    {
      "code": "005490",
      "name": "POSCO홀딩스",
      "price": 342500,
      "change": 0,
      "changePercent": 3.0,
      "volume": 0,
      "direction": "flat"
    },
    {
      "code": "035420",
      "name": "NAVER",
      "price": 211500,
      "change": 0,
      "changePercent": 3.0,
      "volume": 0,
      "direction": "flat"
    },
    {
      "code": "051910",
      "name": "LG화학",
      "price": 314000,
      "change": 0,
      "changePercent": 3.0,
      "volume": 0,
      "direction": "flat"
    },
    {
      "code": "006400",
      "name": "삼성SDI",
      "price": 396500,
      "change": 0,
      "changePercent": 3.0,
      "volume": 0,
      "direction": "flat"
    },
    {
      "code": "035720",
      "name": "카카오",
      "price": 48650,
      "change": 0,
      "changePercent": 3.0,
      "volume": 0,
      "direction": "flat"
    },
    {
      "code": "028260",
      "name": "삼성물산",
      "price": 278000,
      "change": 0,
      "changePercent": 3.0,
      "volume": 0,
      "direction": "flat"
    },
    {
      "code": "012330",
      "name": "현대모비스",
      "price": 398500,
      "change": 0,
      "changePercent": 3.0,
      "volume": 0,
      "direction": "flat"
    },
    {
      "code": "066570",
      "name": "LG전자",
      "price": 113000,
      "change": 0,
      "changePercent": 3.0,
      "volume": 0,
      "direction": "flat"
    },
    {
      "code": "003550",
      "name": "LG",
      "price": 87500,
      "change": 0,
      "changePercent": 3.0,
      "volume": 0,
      "direction": "flat"
    },
    {
      "code": "017670",
      "name": "SK텔레콤",
      "price": 80000,
      "change": 0,
      "changePercent": 3.0,
      "volume": 0,
      "direction": "flat"
    },
    {
      "code": "096770",
      "name": "SK이노베이션",
      "price": 111300,
      "change": 0,
      "changePercent": 3.0,
      "volume": 0,
      "direction": "flat"
    },
    {
      "code": "000270",
      "name": "기아",
      "price": 154700,
      "change": 0,
      "changePercent": 3.0,
      "volume": 0,
      "direction": "flat"
    },
    {
      "code": "005380",
      "name": "현대차",
      "price": 490000,
      "change": 0,
      "changePercent": 3.0,
      "volume": 0,
      "direction": "flat"
    },
    {
      "code": "105560",
      "name": "KB금융",
      "price": 152200,
      "change": 0,
      "changePercent": 3.0,
      "volume": 0,
      "direction": "flat"
    },
    {
      "code": "055550",
      "name": "신한지주",
      "price": 93400,
      "change": 0,
      "changePercent": 3.0,
      "volume": 0,
      "direction": "flat"
    },
    {
      "code": "086790",
      "name": "하나금융지주",
      "price": 108800,
      "change": 0,
      "changePercent": 3.0,
      "volume": 0,
      "direction": "flat"
    }
  ]
}